Metadata-Version: 2.1
Name: carp-python-api-async
Version: 1.0.0
Summary: The [C]openh[A]gen Center for Health Technology [R]esearch [P]latform (CARP) enables researchers to run mobile health (mHealth) studies where data is collected on participant's smartphones and wearable devices. Data is securely uploaded and managed in a hosting infrastructure managed by the Technical University of Denmark (DTU).
Home-page: https://carp.cachet.dk
Author: Alban Maxhuni, PhD
Author-email: almax@dtu.dk
License: CACHET Research Platform
Project-URL: CARP Client API Async - Library, https://github.com/cph-cachet/carp.python-client-api-async
Keywords: carp-python-api-async
Platform: UNKNOWN
Classifier: Programming Language :: Python :: 3
Classifier: License :: OSI Approved :: MIT License
Classifier: Operating System :: OS Independent
License-File: LICENCE.md
Requires-Dist: setuptools
Requires-Dist: requests
Requires-Dist: carp
Requires-Dist: pandas
Requires-Dist: urllib3
Requires-Dist: utils
Requires-Dist: numpy
Requires-Dist: argparse
Requires-Dist: wheel
Requires-Dist: Jinja2
Requires-Dist: Werkzeug
Requires-Dist: matplotlib
Requires-Dist: seaborn
Requires-Dist: pip
Requires-Dist: tqdm
Requires-Dist: twine
